terraform_backend_s3_bucket/__init__.py
terraform_backend_s3_bucket/py.typed
terraform_backend_s3_bucket/_jsii/__init__.py
terraform_backend_s3_bucket/_jsii/terraform-backend-s3-bucket@1.0.18.jsii.tgz
terraform_backend_s3_bucket-1.0.18.dist-info/LICENSE
terraform_backend_s3_bucket-1.0.18.dist-info/METADATA
terraform_backend_s3_bucket-1.0.18.dist-info/WHEEL
terraform_backend_s3_bucket-1.0.18.dist-info/top_level.txt
terraform_backend_s3_bucket-1.0.18.dist-info/RECORD
